<?xml version="1.0" encoding="utf-8" ?>
<hibernate-mapping xmlns="urn:nhibernate-mapping-2.2">
 	<class name="com.LocalSystem.Entity.MasterData.Supplier, com.LocalSystem.Entity" table="Supplier" lazy="false">
		<id name="Code" column="Code" type="String" unsaved-value="null" >
      		<generator class="assigned" />
        </id>
		<property name="Name" column="Name" type="String" length="50" />	
		<property name="Address" column="Address" type="String" length="255" />	
		<property name="Contact" column="Contact" type="String" length="50" />	
		<property name="Fax" column="Fax" type="String" length="50" />	
		<property name="Phone" column="Phone" type="String" length="50" />	
		<property name="CreateUser" column="CreateUser" type="String" length="50" />	
		<property name="CreateDate" column="CreateDate" type="DateTime"  />	
		<property name="LastmodifyUser" column="LastmodifyUser" type="String" length="50" />	
		<property name="LastmodifyDate" column="LastmodifyDate" type="DateTime"  />
    <property name="Carrier" column="Carrier" type="String" length="50" />
    <property name="IsActive" column="IsActive" type="Boolean"  />
    <property name="LeadTime" column="LeadTime" type="Decimal"  />
  	</class>
</hibernate-mapping>
